nonebot_plugin_easyCommand/__init__.py
nonebot_plugin_easyCommand/utils.py
nonebot_plugin_easycommand-1.1.4.dist-info/LICENSE
nonebot_plugin_easycommand-1.1.4.dist-info/METADATA
nonebot_plugin_easycommand-1.1.4.dist-info/WHEEL
nonebot_plugin_easycommand-1.1.4.dist-info/RECORD
