Metadata-Version: 2.1
Name: nonebot-plugin-easycommand
Version: 1.1.4
Summary: 一款基于NoneBot2的简单的用来扩充命令或添加定时任务的插件。
License: MIT
Author: ziru-w
Author-email: 77319678+ziru-w@users.noreply.github.com
Requires-Python: >=3.6,<4.0
Classifier: License :: OSI Approved :: MIT License
Classifier: Programming Language :: Python :: 3
Classifier: Programming Language :: Python :: 3.6
Classifier: Programming Language :: Python :: 3.7
Classifier: Programming Language :: Python :: 3.8
Classifier: Programming Language :: Python :: 3.9
Classifier: Programming Language :: Python :: 3.10
Classifier: Programming Language :: Python :: 3.11
Requires-Dist: nonebot-adapter-onebot (>=2.0.0-beta.1)
Requires-Dist: nonebot2 (>=2.0.0-beta.1)
Requires-Dist: nonebot_plugin_apscheduler
Requires-Dist: nonebot_plugin_txt2img
